servicex_coffea/__init__.py
servicex_coffea/accumulator.py
servicex_coffea/analysis.py
servicex_coffea/dask_executor.py
servicex_coffea/data_source.py
servicex_coffea/executor.py
servicex_coffea/local_executor.py
servicex_coffea/schema.py
servicex_coffea/sx_qastle.py
servicex_coffea-0.0.1a0.dist-info/LICENSE
servicex_coffea-0.0.1a0.dist-info/METADATA
servicex_coffea-0.0.1a0.dist-info/WHEEL
servicex_coffea-0.0.1a0.dist-info/top_level.txt
servicex_coffea-0.0.1a0.dist-info/RECORD
