Metadata-Version: 2.1
Name: servicex-coffea
Version: 0.0.1a0
Summary: Analyze ServiceX Data Using Coffea Tools
Home-page: https://github.com/cloudtools/troposphere
Author: Ben Galewsky
Author-email: bengal1@illinois.edu
License: New BSD license
Project-URL: Changelog, https://github.com/cloudtools/troposphere/blob/master/CHANGELOG.md
Project-URL: Source, https://github.com/cloudtools/troposphere
Project-URL: Tracker, https://github.com/cloudtools/troposphere/issues
Platform: UNKNOWN
Classifier: Development Status :: 3 - Alpha
Classifier: Intended Audience :: Developers
Classifier: Intended Audience :: Information Technology
Classifier: License :: OSI Approved :: BSD License
Classifier: Programming Language :: Python
Classifier: Topic :: Software Development
Classifier: Topic :: Utilities
Classifier: Programming Language :: Python
Classifier: Programming Language :: Python :: 3.6
Classifier: Programming Language :: Python :: 3.7
Classifier: Programming Language :: Python :: 3.8
Requires-Python: >=3.6
Requires-Dist: aiostream
Requires-Dist: tenacity
Requires-Dist: servicex-clients
Requires-Dist: coffea
Provides-Extra: dask
Requires-Dist: dask ; extra == 'dask'
Requires-Dist: distributed ; extra == 'dask'
